{
"type": "FeatureCollection",
"name": "geo_10_介護医療院",
"crs": { "type": "name", "properties": { "name": "urn:ogc:def:crs:OGC:1.3:CRS84" } },
"features": [
{ "type": "Feature", "properties": { "内容": "介護医療院ふえき【介護医療院】群馬県前橋市表町２丁目27-22前橋ふえきクリニック（介護医療院ふえき）", "url": "https://www.kaigokensaku.mhlw.go.jp/10/index.php?action_kouhyou_detail_004_kani=true&JigyosyoCd=10B0100010-00&ServiceCd=550&Type=search", "url2": "http://ubukatakai.webmedipr.jp/contents/about.html" }, "geometry": { "type": "Point", "coordinates": [ 139.074624991643134, 36.384686270865785 ] } },
{ "type": "Feature", "properties": { "内容": "松岡医院介護医療院【介護医療院】群馬県高崎市片岡町1丁目17番31号", "url": "https://www.kaigokensaku.mhlw.go.jp/10/index.php?action_kouhyou_detail_004_kani=true&JigyosyoCd=10B0200018-00&ServiceCd=550&Type=search", "url2": null }, "geometry": { "type": "Point", "coordinates": [ 138.996766900000011, 36.3184047 ] } },
{ "type": "Feature", "properties": { "内容": "医療法人　慶仁会　城山病院　介護医療医療院【介護医療院】群馬県太田市飯塚町1番地", "url": "https://www.kaigokensaku.mhlw.go.jp/10/index.php?action_kouhyou_detail_004_kani=true&JigyosyoCd=10B0500011-00&ServiceCd=550&Type=search", "url2": "https://www.shiroyama-hospital.or.jp/" }, "geometry": { "type": "Point", "coordinates": [ 139.3789504, 36.2800551 ] } },
{ "type": "Feature", "properties": { "内容": "介護医療院　冨士ヶ丘病院【介護医療院】群馬県太田市熊野町３８－８１", "url": "https://www.kaigokensaku.mhlw.go.jp/10/index.php?action_kouhyou_detail_004_kani=true&JigyosyoCd=10B0500029-00&ServiceCd=550&Type=search", "url2": "http://www.fujigaoka-hosp.jp/" }, "geometry": { "type": "Point", "coordinates": [ 139.384289200000012, 36.3074686 ] } },
{ "type": "Feature", "properties": { "内容": "新橋病院　介護医療院【介護医療院】群馬県館林市下三林市452番地", "url": "https://www.kaigokensaku.mhlw.go.jp/10/index.php?action_kouhyou_detail_004_kani=true&JigyosyoCd=10B0700017-00&ServiceCd=550&Type=search", "url2": "https://www.shinbashi.or/" }, "geometry": { "type": "Point", "coordinates": [ 139.5050946, 36.2228047 ] } },
{ "type": "Feature", "properties": { "内容": "介護医療院　しのづか【介護医療院】群馬県藤岡市篠塚105-1", "url": "https://www.kaigokensaku.mhlw.go.jp/10/index.php?action_kouhyou_detail_004_kani=true&JigyosyoCd=10B0900013-00&ServiceCd=550&Type=search", "url2": "http://www.shinozuka-hp.or.jp" }, "geometry": { "type": "Point", "coordinates": [ 139.0647439, 36.2588617 ] } },
{ "type": "Feature", "properties": { "内容": "西毛病院介護医療院【介護医療院】群馬県富岡市神農原559-1", "url": "https://www.kaigokensaku.mhlw.go.jp/10/index.php?action_kouhyou_detail_004_kani=true&JigyosyoCd=10B1000029-00&ServiceCd=550&Type=search", "url2": "http://www.seimou.org/" }, "geometry": { "type": "Point", "coordinates": [ 138.840873003704786, 36.243884336007433 ] } },
{ "type": "Feature", "properties": { "内容": "介護医療院　細谷【介護医療院】群馬県　富岡市富岡1375番地", "url": "https://www.kaigokensaku.mhlw.go.jp/10/index.php?action_kouhyou_detail_004_kani=true&JigyosyoCd=10B1000011-00&ServiceCd=550&Type=search", "url2": "https://www.hosoya.or.jp" }, "geometry": { "type": "Point", "coordinates": [ 138.893994849073806, 36.257747037602485 ] } },
{ "type": "Feature", "properties": { "内容": "介護医療院　本多病院【介護医療院】群馬県安中市鷺宮205-1", "url": "https://www.kaigokensaku.mhlw.go.jp/10/index.php?action_kouhyou_detail_004_kani=true&JigyosyoCd=10B1100019-00&ServiceCd=550&Type=search", "url2": "http://www.honda-hospital.jp/" }, "geometry": { "type": "Point", "coordinates": [ 138.8969105, 36.3051851 ] } },
{ "type": "Feature", "properties": { "内容": "みどり病院介護医療院【介護医療院】群馬県みどり市笠懸町鹿2646-2", "url": "https://www.kaigokensaku.mhlw.go.jp/10/index.php?action_kouhyou_detail_004_kani=true&JigyosyoCd=10B1200017-00&ServiceCd=550&Type=search", "url2": "https://sunhope.or.jp" }, "geometry": { "type": "Point", "coordinates": [ 139.2813706, 36.4002995 ] } },
{ "type": "Feature", "properties": { "内容": "下仁田南牧医療事務組合下仁田厚生病院介護医療院【介護医療院】群馬県甘楽郡下仁田町大字下仁田４０９", "url": "https://www.kaigokensaku.mhlw.go.jp/10/index.php?action_kouhyou_detail_004_kani=true&JigyosyoCd=10B2400012-00&ServiceCd=550&Type=search", "url2": "https://www.shimonitakosei-hosp.jp/" }, "geometry": { "type": "Point", "coordinates": [ 138.78604, 36.2131455 ] } },
{ "type": "Feature", "properties": { "内容": "吾妻さくら病院介護医療院【介護医療院】群馬県吾妻郡中之条町大字伊勢町782-1", "url": "https://www.kaigokensaku.mhlw.go.jp/10/index.php?action_kouhyou_detail_004_kani=true&JigyosyoCd=10B2600017-00&ServiceCd=550&Type=search", "url2": "http://www.a-sakurahosp.com/" }, "geometry": { "type": "Point", "coordinates": [ 138.853027, 36.5859438 ] } }
]
}
